ImpedancePy/__init__.py
ImpedancePy/shock_wave_compression/BackwardPropagationFromWindow.py
ImpedancePy/shock_wave_compression/ShockWaveExperiment.py
ImpedancePy/shock_wave_compression/__init__.py
ImpedancePy/shock_wave_compression/material_database/Kapton.py
ImpedancePy/shock_wave_compression/material_database/MgO.py
ImpedancePy/shock_wave_compression/material_database/Quartz.py
ImpedancePy/shock_wave_compression/material_database/__init__.py
ImpedancePy/shock_wave_compression/material_database/baseclass/Material.py
ImpedancePy/shock_wave_compression/material_database/baseclass/__init__.py
ImpedancePy/shock_wave_compression/material_states/Hugoniot.py
ImpedancePy/shock_wave_compression/material_states/Intersection.py
ImpedancePy/shock_wave_compression/material_states/Isentrope.py
ImpedancePy/shock_wave_compression/material_states/__init__.py
ImpedancePy/shock_wave_compression/material_states/isentrope_calculators/IntegratedIsentrope.py
ImpedancePy/shock_wave_compression/material_states/isentrope_calculators/ReflectedHugoniot.py
ImpedancePy/shock_wave_compression/material_states/isentrope_calculators/__init__.py
ImpedancePy-0.1.28.dist-info/METADATA
ImpedancePy-0.1.28.dist-info/WHEEL
ImpedancePy-0.1.28.dist-info/top_level.txt
ImpedancePy-0.1.28.dist-info/RECORD
